bst_plugins_container/__init__.py
bst_plugins_container/elements/__init__.py
bst_plugins_container/elements/docker_image.py
bst_plugins_container/elements/docker_image.yaml
bst_plugins_container/sources/__init__.py
bst_plugins_container/sources/docker.py
bst_plugins_container-0.4.1.dist-info/LICENSE
bst_plugins_container-0.4.1.dist-info/METADATA
bst_plugins_container-0.4.1.dist-info/WHEEL
bst_plugins_container-0.4.1.dist-info/entry_points.txt
bst_plugins_container-0.4.1.dist-info/top_level.txt
bst_plugins_container-0.4.1.dist-info/RECORD
