Metadata-Version: 2.1
Name: bst-plugins-container
Version: 0.4.1
Summary: A collection of BuildStream plugins that are related to containers.
Home-page: UNKNOWN
Author: BuildStream Developers
Author-email: dev@buildstream.apache.org
License: LGPL
Project-URL: Source, https://gitlab.com/BuildStream/bst-plugins-container
Project-URL: Documentation, https://buildstream.gitlab.io/bst-plugins-container/
Project-URL: Tracker, https://gitlab.com/BuildStream/bst-plugins-container/issues
Project-URL: Mailing List, https://lists.apache.org/list.html?dev@buildstream.apache.org
Platform: UNKNOWN
Classifier: Environment :: Console
Classifier: Intended Audience :: Developers
Classifier: License :: OSI Approved :: GNU Lesser General Public License v2 or later (LGPLv2+)
Classifier: Operating System :: POSIX
Classifier: Programming Language :: Python :: 3
Classifier: Programming Language :: Python :: 3.6
Classifier: Programming Language :: Python :: 3.7
Classifier: Programming Language :: Python :: 3.8
Classifier: Topic :: Software Development :: Build Tools
Requires-Python: >=3.6
Requires-Dist: requests
